fichub_cli/__init__.py
fichub_cli/cli.py
fichub_cli/utils/__init__.py
fichub_cli/utils/fetch_data.py
fichub_cli/utils/fichub.py
fichub_cli/utils/logging.py
fichub_cli/utils/processing.py
fichub_cli-0.10.3.dist-info/LICENSE.txt
fichub_cli-0.10.3.dist-info/METADATA
fichub_cli-0.10.3.dist-info/WHEEL
fichub_cli-0.10.3.dist-info/entry_points.txt
fichub_cli-0.10.3.dist-info/top_level.txt
fichub_cli-0.10.3.dist-info/RECORD
