Metadata-Version: 2.1
Name: fichub-cli
Version: 0.10.3
Summary: A CLI for the fichub.net API
Home-page: https://github.com/FicHub/fichub-cli
Author: Arbaaz Laskar
Author-email: arzkar.dev@gmail.com
License: Apache License
Classifier: Programming Language :: Python :: 3
Classifier: License :: OSI Approved :: Apache Software License
Classifier: Operating System :: OS Independent
License-File: LICENSE.txt
Requires-Dist: typer >=0.4.0
Requires-Dist: requests >=2.31.0
Requires-Dist: loguru >=0.6.0
Requires-Dist: tqdm >=4.60.0
Requires-Dist: BeautifulSoup4 >=4.9.3
Requires-Dist: colorama >=0.4.4
Requires-Dist: platformdirs >=2.5.1
